setup.py
xss_catcher/__init__.py
xss_catcher/xss_catcher.py
xss_catcher.egg-info/PKG-INFO
xss_catcher.egg-info/SOURCES.txt
xss_catcher.egg-info/dependency_links.txt
xss_catcher.egg-info/entry_points.txt
xss_catcher.egg-info/top_level.txt