Metadata-Version: 1.1
Name: xss-catcher
Version: 0.0.1
Summary: Simple pythonic script to catch Cross Site Scripting (XSS) connections
Home-page: https://github.com/owlz/xss_catcher
Author: Michael Bann
Author-email: self@bannsecurity.com
License: MIT
Keywords: xss
Platform: UNKNOWN
Classifier: Development Status :: 5 - Production/Stable
Classifier: Intended Audience :: End Users/Desktop
Classifier: License :: OSI Approved :: MIT License
Classifier: Programming Language :: Python :: 3
Classifier: Operating System :: POSIX :: Linux
Classifier: Environment :: Console
